Workbook

Sheet     合 同    
A1: JIESONG INTERNATIONAL LOGISTICS CO., LTD 上海捷淞国际物流有限公司
A2: 销售合同 SALES CONFIRMATION | H2: 威斯敏
F3: NO.: EXP260008
F4: Date: Jun.15, 2026
A5: Seller: | B5: 上海捷淞国际物流有限公司 JIESONG INTERNATIONAL LOGISTICS CO., LTD C / F, 888 Huanhu West second Road, Lingang New District, China (Shanghai) Free Trade Experimental Zone / 201306
A6: Buyers: | B6: Sp food trading LLC
A7: 兹买卖双方同意就以下条款达成协议： This Contract is made by and between the Buyers and the Sellers, whereby the Buyers agree to buy and the Sellers agree to sell the under mentioned commodity according to the terms and conditions stipulated below:
A8: Item | B8: 货物名称及规格 Name of Commodity and Specifications | C8: 包装 Package | D8: 数量(单位） Quantity | E8: 单价(USD） （EXW SHANGHAI） Unit Price Per Box | F8: 总价 （EXW SHANGHAI） Total Amount(USD)
A9: 1 | B9: 铁艺屏风 | C9: 2450*340*1540 | D9: 2 | E9: 5000 | F9: =ROUNDUP(E9*D9,1) -> 10000
A10: 2 | B10: 自助餐台 | C10: 3148*1611*1150 | D10: 1 | E10: 7000 | F10: =ROUNDUP(E10*D10,1) -> 7000
A11: 3 | B11: 1.2米常温调酒台 | C11: 1300*700*1000 | D11: 3 | E11: 400 | F11: =ROUNDUP(E11*D11,1) -> 1200
A12: 4 | B12: 金属蜂窝板 | C12: 2050*1250*430 | D12: 22.8 | E12: 90 | F12: =ROUNDUP(E12*D12,1) -> 2052
A13: 5 | B13: 酒架 | C13: 1980*370*1020 | D13: 1 | E13: 1400 | F13: =ROUNDUP(E13*D13,1) -> 1400
A14: 6 | B14: 隔断 | C14: 2900*360*1195 | D14: 1 | E14: 3000 | F14: =ROUNDUP(E14*D14,1) -> 3000
A15: 7 | B15: 瓷砖 | C15: 800*800*40 | D15: 232 | E15: 13 | F15: =ROUNDUP(E15*D15,1) -> 3016
A16: 总计 TOTOL | D16: =SUM(D9:D15) -> 262.8 | F16: =SUM(F9:F15) -> 27668
A17: （1）交货期：120days after the receiving of payment.
A18: （2）起运港：FROM SHENZHEN, CHINA TO USA
A19: （3）Trade term: SHENZHEN warehouse.
A20: （4）Terms of payment：T/T. 100% contract value paid in advance.
A21: （5）Packing: To be packed in standard ocean shipping packing.
A23: BANK ACCOUNT INFO:
A25: Beneficiary Name: Jiesong International Logistics Co., Ltd.
A26: Beneficiary Account No: CHINA MERCHANTS BANK 121952808032001
A27: Bank Address: NO.1800 JIANGYUE ROAD,SHANGHAI ,CHINA
A28: SWIFT code: CMBCCNBS
A29: CNAPS code: 308290003749
A34: SELLER: | D34: BUYER:
A35: =B5 -> 上海捷淞国际物流有限公司 JIESONG INTERNATIONAL LOGISTICS CO., LTD C / F, 888 Huanhu West second Road, Lingang New District, China (Shanghai) Free Trade Experimental Zone / 201306 | D35: =B6 -> Sp food trading LLC

Sheet 发   票
A1: =' 合 同 '!A1 -> JIESONG INTERNATIONAL LOGISTICS CO., LTD 上海捷淞国际物流有限公司
A2: 发票 COMMERCIAL INVOICE
F3: =' 合 同 '!F3 -> NO.: EXP260008
F4: =' 合 同 '!F4 -> Date: Jun.15, 2026
A5: Seller: | B5: =' 合 同 '!B5 -> 上海捷淞国际物流有限公司 JIESONG INTERNATIONAL LOGISTICS CO., LTD C / F, 888 Huanhu West second Road, Lingang New District, China (Shanghai) Free Trade Experimental Zone / 201306
A6: Buyers: | B6: =' 合 同 '!B6 -> Sp food trading LLC
A7: 兹买卖双方同意就以下条款达成协议： This Contract is made by and between the Buyers and the Sellers, whereby the Buyers agree to buy and the Sellers agree to sell the under mentioned commodity according to the terms and conditions stipulated below:
A8: Item | B8: 货物名称及规格 Name of Commodity and Specifications | C8: 包装 Package | D8: =' 合 同 '!D8 -> 数量(单位） Quantity | E8: 单价(USD） （EXW SHANGHAI） Unit Price Per Box | F8: 总价 （EXW SHANGHAI） Total Amount(USD)
A9: 1 | B9: 铁艺屏风 | C9: =' 合 同 '!C9 -> 2450*340*1540 | D9: =' 合 同 '!D9 -> 2 | E9: =' 合 同 '!E9 -> 5000 | F9: =' 合 同 '!F9 -> 10000
A10: 2 | B10: 自助餐台 | C10: =' 合 同 '!C10 -> 3148*1611*1150 | D10: =' 合 同 '!D10 -> 1 | E10: =' 合 同 '!E10 -> 7000 | F10: =' 合 同 '!F10 -> 7000
A11: 3 | B11: 1.2米常温调酒台 | C11: =' 合 同 '!C11 -> 1300*700*1000 | D11: =' 合 同 '!D11 -> 3 | E11: =' 合 同 '!E11 -> 400 | F11: =' 合 同 '!F11 -> 1200
A12: 4 | B12: 金属蜂窝板 | C12: =' 合 同 '!C12 -> 2050*1250*430 | D12: =' 合 同 '!D12 -> 22.8 | E12: =' 合 同 '!E12 -> 90 | F12: =' 合 同 '!F12 -> 2052
A13: 5 | B13: 酒架 | C13: =' 合 同 '!C13 -> 1980*370*1020 | D13: =' 合 同 '!D13 -> 1 | E13: =' 合 同 '!E13 -> 1400 | F13: =' 合 同 '!F13 -> 1400
A14: 6 | B14: 隔断 | C14: =' 合 同 '!C14 -> 2900*360*1195 | D14: =' 合 同 '!D14 -> 1 | E14: =' 合 同 '!E14 -> 3000 | F14: =' 合 同 '!F14 -> 3000
A15: 7 | B15: 瓷砖 | C15: =' 合 同 '!C15 -> 800*800*40 | D15: =' 合 同 '!D15 -> 232 | E15: =' 合 同 '!E15 -> 13 | F15: =' 合 同 '!F15 -> 3016
A16: 总计 TOTOL | D16: =SUM(D9:D15) -> 262.8 | F16: =SUM(F9:F15) -> 27668
A17: =' 合 同 '!A17 -> （1）交货期：120days after the receiving of payment.
A18: =' 合 同 '!A18 -> （2）起运港：FROM SHENZHEN, CHINA TO USA
A19: =' 合 同 '!A19 -> （3）Trade term: SHENZHEN warehouse.
A20: （4）Terms of payment：T/T. 100% contract value paid in advance.
A21: （5）Packing: To be packed in standard ocean shipping packing.
A23: BANK ACCOUNT INFO:
A25: Beneficiary Name: Jiesong International Logistics Co., Ltd.
A26: Beneficiary Account No: CHINA MERCHANTS BANK 121952808032001
A27: Bank Address: NO.1800 JIANGYUE ROAD,SHANGHAI ,CHINA
A28: SWIFT code: CMBCCNBS
A29: CNAPS code: 308290003749
A34: SELLER: | D34: BUYER:
A35: =B5 -> 上海捷淞国际物流有限公司 JIESONG INTERNATIONAL LOGISTICS CO., LTD C / F, 888 Huanhu West second Road, Lingang New District, China (Shanghai) Free Trade Experimental Zone / 201306 | D35: =B6 -> Sp food trading LLC

Sheet 箱   单 
A1: ='[1] 合 同 '!A1 -> JIESONG INTERNATIONAL LOGISTICS CO., LTD 上海捷淞国际物流有限公司
A2: 装箱单 PACKING LIST
H3: =' 合 同 '!F3 -> NO.: EXP260008
H4: ='发 票'!F4 -> Date: Jun.15, 2026
A5: Seller: | B5: ='[1] 合 同 '!B5 -> 上海捷淞国际物流有限公司 JIESONG INTERNATIONAL LOGISTICS CO., LTD C / F, 888 Huanhu West second Road, Lingang New District, China (Shanghai) Free Trade Experimental Zone / 201306
A6: Buyers: | B6: ='[1] 合 同 '!B6 -> Sp food trading LLC
A7: 兹买卖双方同意就以下条款达成协议： This Contract is made by and between the Buyers and the Sellers, whereby the Buyers agree to buy and the Sellers agree to sell the under mentioned commodity according to the terms and conditions stipulated below:
A8: Item | B8: 货物名称及规格 Name of Commodity and Specifications | C8: HSCODE | D8: 尺寸 | E8: 数量（箱） | F8: 毛重（kg） | G8: 净重（kg） | H8: 体积(立方米m³） | I8: 数量 | J8: 单位 | K8: 申报明细 | L8: 货源地
A9: 1 | B9: 铁艺屏风 | C9: =VLOOKUP(B9,[2]货品目录!$B:$C,2,0) -> 8306299000 | D9: 2450*340*1540 | E9: 22 | F9: 1528 | G9: 1450 | H9: 23.93 | I9: 2 | J9: 套 | K9: =VLOOKUP(B9,[2]货品目录!$B:$M,12,0) -> 0|0|碳钢管|屏风|未镀贵金属|非铃、钟、锣|无品牌|方管4*4 3*3 | L9: =VLOOKUP(B9,[2]货品目录!$B:$M,11,0) -> 泉州市安溪县
A10: 2 | B10: 自助餐台 | C10: =VLOOKUP(B10,[2]货品目录!$B:$C,2,0) -> 8419810000 | D10: 3148*1611*1150 | E10: 3 | F10: 875 | G10: 800 | H10: 7.8 | I10: 1 | J10: 套 | K10: =VLOOKUP(B10,[2]货品目录!$B:$M,12,0) -> 0|0|金属框架配石质台面，配有不锈钢餐槽及保温系统|无品牌|无型号| | L10: =VLOOKUP(B10,[2]货品目录!$B:$M,11,0) -> 广东省广州市
A11: 3 | B11: 1.2米常温调酒台 | C11: =VLOOKUP(B11,[2]货品目录!$B:$C,2,0) -> 9403200000 | D11: 1300*700*1000 | E11: 3 | F11: 180 | G11: 170 | H11: 1.82 | I11: 3 | J11: 台 | K11: =VLOOKUP(B11,[2]货品目录!$B:$M,12,0) -> 0|0|用于搁置调酒器皿|不锈钢|无品牌|1.2米长| | L11: =VLOOKUP(B11,[2]货品目录!$B:$M,11,0) -> 广州市番禺区
A12: 4 | B12: 金属蜂窝板 | C12: =VLOOKUP(B12,[2]货品目录!$B:$C,2,0) -> 7326909000 | D12: 2050*1250*430 | E12: 3 | F12: 258 | G12: 250 | H12: 1.161 | I12: 22.8 | J12: 平方米 | K12: =VLOOKUP(B12,[2]货品目录!$B:$M,12,0) -> 0|0|非工业用|外层不锈钢板，内层铝蜂窝芯|切割成型并封边| | L12: =VLOOKUP(B12,[2]货品目录!$B:$M,11,0) -> 广东省佛山市
A13: 5 | B13: 酒架 | C13: =VLOOKUP(B13,[2]货品目录!$B:$C,2,0) -> 7326909000 | D13: 1980*370*1020 | E13: 1 | F13: 149.3 | G13: 145 | H13: 4.305 | I13: 1 | J13: 套 | K13: =VLOOKUP(B13,[2]货品目录!$B:$M,12,0) -> 0|0|非工业用|不锈钢30*30方管|不锈钢拼接而成，使用钢化玻璃承接| | L13: =VLOOKUP(B13,[2]货品目录!$B:$M,11,0) -> 泉州市安溪县
A14: 6 | B14: 隔断 | C14: =VLOOKUP(B14,[2]货品目录!$B:$C,2,0) -> 9403200000 | D14: 2900*360*1195 | E14: 1 | F14: 530 | G14: 460 | H14: 1.25 | I14: 1 | J14: 套 | K14: =VLOOKUP(B14,[2]货品目录!$B:$M,12,0) -> 0|0|用于餐厅包厢门及空间隔断装饰|不锈钢主题搭配金属装饰条|无品牌|1681*2674mm| | L14: =VLOOKUP(B14,[2]货品目录!$B:$M,11,0) -> 广东省广州市
A15: 7 | B15: 瓷砖 | C15: =VLOOKUP(B15,[2]货品目录!$B:$C,2,0) -> 6907219000 | D15: 800*800*40 | E15: 250 | F15: 18540 | G15: 18500 | H15: 23.04 | I15: 232 | J15: 平方米 | K15: =VLOOKUP(B15,[2]货品目录!$B:$M,12,0) -> 0|0|铺面砖|800*800|0.003|无品牌|深灰色 | L15: =VLOOKUP(B15,[2]货品目录!$B:$M,11,0) -> 佛山市禅城区
A16: 总计 TOTOL | E16: =SUM(E9:E15) -> 283 | F16: =SUM(F9:F15) -> 22060.3 | G16: =SUM(G9:G15) -> 21775 | H16: =SUM(H9:H15) -> 63.306
A17: SELLER: | E17: BUYER:
A18: =B5 -> 上海捷淞国际物流有限公司 JIESONG INTERNATIONAL LOGISTICS CO., LTD C / F, 888 Huanhu West second Road, Lingang New District, China (Shanghai) Free Trade Experimental Zone / 201306 | E18: =B6 -> Sp food trading LLC

Sheet 装箱清单
A1: 报关名 | B1: 商品补充信息 | C1: 门店 | D1: 港口 | E1: 报关数量 | F1: 单位 | G1: 厂家 | H1: 规格 | I1: 箱数 | J1: 毛重 | K1: 净重 | L1: 体积
A2: 铁艺屏风 | C2: 威斯敏 | D2: 洛杉矶 | E2: 2 | F2: 套 | G2: 福建泉州鼎联工艺品有限公司 | H2: 2450*340*1540 | I2: 22 | J2: 1528 | K2: 1450 | L2: 23.93
A3: 自助餐台 | C3: 威斯敏 | D3: 洛杉矶 | E3: 1 | F3: 套 | G3: 广州布菲厨具制造有限公司 | H3: 3148*1611*1150 | I3: 3 | J3: 875 | K3: 800 | L3: 7.8
A4: 1.2米常温调酒台 | B4: 1左2右 | C4: 威斯敏 | D4: 洛杉矶 | E4: 3 | F4: 台 | G4: 广州市拓盛餐饮设备有限公司 | H4: 1300*700*1000 | I4: 3 | J4: 180 | K4: 170 | L4: 1.82
A5: 金属蜂窝板 | C5: 威斯敏 | D5: 洛杉矶 | E5: 22.8 | F5: 平方米 | G5: 广州高邦装饰材料有限公司 | H5: 2050*1250*430 | I5: 3 | J5: 258 | K5: 250 | L5: 1.161
A6: 酒架 | C6: 威斯敏 | D6: 洛杉矶 | E6: 1 | F6: 套 | H6: 1980*370*1020 | I6: 1 | J6: 149.3 | K6: 145 | L6: 4.305
A7: 隔断 | B7: 包厢隔断门 | C7: 威斯敏 | D7: 洛杉矶 | E7: 1 | F7: 套 | H7: 2900*360*1195 | I7: 1 | J7: 530 | K7: 460 | L7: 1.25
A8: 瓷砖 | B8: 370箱800砖，还有50箱长砖 | C8: 威斯敏 | D8: 洛杉矶 | E8: 232 | F8: 平方米 | H8: 800*800*40 | I8: 250 | J8: 18540 | K8: 18500 | L8: 23.04

Sheet 装货
A1: 序号 | B1: 报关名 | C1: 商品补充信息 | D1: 门店 | E1: 港口 | F1: 报关数量 | G1: 单位 | H1: 厂家 | I1: 规格 | J1: 箱数 | K1: 毛重 | L1: 净重 | M1: 体积 | N1: 柜子编号 | O1: 出货日期 | P1: 合同号 | Q1: 报关公司 | R1: 是否付款 | S1: 备注
A2: 268 | B2: 卡座 | C2: 刘总卡座 | D2: 圣荷西2115 | E2: Oakland | F2: 4 | G2: 件 | H2: 卡座刘总 | I2: 1828*534*1140 | J2: 4 | K2: 480 | L2: 460 | M2: 8.8 | N2: 25-圣荷西混合 | O2: 46008 | P2: EXP250027 | Q2: 其他厂家报关 | S2: 刘总装
A3: 286 | B3: 不锈钢桶 | D3: 圣荷西2115 | E3: Oakland | F3: 10 | G3: 个 | I3: 630*560*1220 | J3: 3 | K3: 141.65 | L3: 140 | M3: 1.317708 | N3: 25-圣荷西混合 | O3: 46008 | P3: EXP250027 | Q3: 捷淞 | R3: 是 | S3: 已经在黎总那
A4: 299 | B4: 椅子 | C4: 高脚椅 | D4: 圣荷西2115 | E4: Oakland | F4: 20 | G4: 把 | H4: 廊坊秀儿商贸 | I4: 480*480*950 | J4: 20 | K4: 232 | L4: 230 | M4: 4.3776 | N4: 25-圣荷西混合 | O4: 46008 | P4: EXP250027 | Q4: 捷淞 | R4: 是 | S4: 已经在黎总那
B5: 窗帘 | C5: 补充窗帘 | D5: 米尔皮塔、圣荷西625、禧瑞都 | E5: 混合港口 | F5: 66 | G5: 套 | H5: 新厂家窗帘 | I5: 1930*210*210 | J5: 12 | K5: 186 | L5: 181 | M5: 0.9038 | N5: 25-圣荷西混合 | O5: 46008 | P5: EXP250027 | Q5: 捷淞 | S5: 12/16送达
A6: 315 | B6: 椅子 | D6: 圣荷西2115 | E6: Oakland | F6: 300 | G6: 把 | H6: 廊坊秀儿商贸 | I6: 790*680*560 | J6: 150 | K6: 2250 | L6: 2200 | M6: 33.6 | N6: 25-圣荷西混合 | O6: 46008 | P6: EXP250027 | Q6: 捷淞 | R6: 是 | S6: 等待派送 | T6: 这个最后塞，能装多少装多少
A7: 316 | B7: LED显示屏 | D7: 圣荷西625 | E7: Oakland | F7: 1 | G7: 套 | H7: 深圳杨总 | I7: 1330*1050*1290 | J7: 2 | K7: 470 | L7: 450 | M7: 2.258139 | N7: 25-圣荷西混合 | O7: 46008 | P7: EXP250027 | Q7: 捷淞 | S7: 12/16送达
A8: 317 | B8: 长方盘 | C8: 各种烤盘，剪刀，夹子 | D8: 圣荷西2115 | E8: Oakland | F8: 2864 | G8: 个 | H8: 台德 | I8: 570*345*350 | J8: 25 | K8: 534.58 | L8: 520 | M8: 0.471 | N8: 25-圣荷西混合 | O8: 46008 | P8: EXP250027 | Q8: 捷淞 | S8: 12/17送达
A9: 319 | B9: 餐盘 | C9: 异形大盘 | D9: 圣荷西2115 | E9: Oakland | F9: 240 | G9: 个 | H9: 王总 | I9: 600*370*470 | J9: 31 | K9: 312 | L9: 300 | M9: 2.14 | N9: 25-圣荷西混合 | O9: 46008 | P9: EXP250027 | Q9: 捷淞 | S9: 12/17送达
A10: 321 | B10: 不锈钢护栏 | C10: 补充直杠 | D10: 禧瑞都 | E10: 洛杉矶 | F10: 1.4 | G10: 米 | H10: 佛山 | I10: 1220*240*300 | J10: 2 | K10: 90.2 | L10: 85 | M10: 0.164 | N10: 25-圣荷西混合 | O10: 46008 | P10: EXP250027 | Q10: 捷淞 | S10: 12/16送达
A11: 322 | B11: 餐边柜 | D11: 圣荷西2115 | E11: Oakland | F11: 2 | G11: 件 | H11: 上海定制 | I11: 635*1780*1340 | J11: 2 | K11: 226.8 | L11: 200 | M11: 3.029204 | N11: 25-圣荷西混合 | O11: 46008 | P11: EXP250027 | Q11: 捷淞 | R11: 是 | S11: 货满满运输（徐总发）
A12: 323 | B12: 卡座 | C12: 刘总卡座 | D12: 米尔皮塔 | E12: Oakland | F12: 29 | G12: 件 | H12: 卡座刘总 | I12: 1828*534*1140 | J12: 28 | K12: 692 | L12: 680 | M12: 17.5 | N12: 25-圣荷西混合 | O12: 46008 | P12: EXP250027 | Q12: 其他厂家报关 | S12: 刘总装
A13: 324 | B13: 瓷砖 | C13: 寒江雪 | D13: Burbank | E13: 洛杉矶 | F13: 27.36 | G13: 平方米 | H13: 黎总 | I13: 600*1200*20 | J13: 19 | K13: 900 | L13: 880 | M13: 0.4 | N13: 25-圣荷西混合 | O13: 46008 | P13: EXP250027 | Q13: 捷淞 | R13: 是 | S13: 已经在黎总那
A14: 325 | B14: 大理石材 | C14: 收银台，洗手盘，酒吧吧台 | D14: 米尔皮塔 | E14: Oakland | F14: 25 | G14: 件 | H14: 振宗 | I14: 2270*530*950 | J14: 5 | K14: 1050 | L14: 1000 | M14: 6.702 | N14: 25-圣荷西混合 | O14: 46008 | P14: EXP250027 | Q14: 捷淞 | S14: 振宗12/17派送
A15: 327 | B15: 亚克力板 | D15: 圣荷西2115 | E15: Oakland | F15: 27 | G15: 张 | H15: 亚克力 | I15: 2500*1300*490 | J15: 1 | K15: 1073 | L15: 1052 | M15: 1.6 | N15: 25-圣荷西混合 | O15: 46008 | P15: EXP250027 | Q15: 捷淞 | S15: 12/17厂家派送
A16: 328 | B16: 小型饭团机 | C16: 饭团机+铺饭机 | D16: 圣荷西625 | E16: Oakland | F16: 2 | G16: 台 | H16: 宜拓 | I16: 690*450*695 | J16: 2 | K16: 64 | L16: 60 | M16: 0.26 | N16: 25-圣荷西混合 | O16: 46008 | P16: EXP250027 | Q16: 捷淞 | S16: 12/16送达
A17: 334 | B17: 人造石英石制品 | C17: 搭配收银台 | D17: 米尔皮塔 | E17: Oakland | F17: 110 | G17: 平方米 | H17: 新兴石材 | I17: 3200*1600*20 | J17: 2 | K17: 500 | L17: 490 | M17: 2.048 | N17: 27-圣荷西2115 | O17: 46008 | P17: EXP250027 | Q17: 捷淞 | R17: 是 | S17: 不用管，属于加工附属
B18: 档边玻璃 | C18: 预计12/17送达，涂经理配送

Sheet 发票汇总
A1: 序号 | B1: 产品 | C1: 单位 | D1: 数量 | E1: 单价（不含税） | F1: 金额 | G1: 税率 | H1: 税额 | I1: 总金额 | J1: 报关单号 | K1: 发票号码 | L1: 开票日期 | M1: 纳税人识别号 | O1: 530420240040849246
A2: 1 | B2: 传送带 | C2: 千克 | D2: 395 | E2: 85.239 | F2: =E2*D2 -> 33669.405 | G2: 0.03 | H2: =F2*G2 -> 1010.0821 | I2: =F2+H2 -> 34679.487 | J2: =O$1&TEXT(A2,"000") -> 530420240040849246001 | K2: 24442000000246727571 | L2: 2024-06-11 | M2: 91440101094203844N | O2: EXP2400001
A3: 2 | B3: 传送带 | C3: 千克 | D3: 250 | E3: 85.239 | F3: =E3*D3 -> 21309.75 | G3: 0.03 | H3: =F3*G3 -> 639.2925 | I3: =F3+H3 -> 21949.042 | J3: =O$1&TEXT(A3,"000") -> 530420240040849246002 | K3: 24442000000246736253 | L3: 2024-06-11 | M3: 91440101094203844N
A4: 3 | B4: 传送带 | C4: 千克 | D4: 120 | E4: 85.239 | F4: =E4*D4 -> 10228.68 | G4: 0.03 | H4: =F4*G4 -> 306.8604 | I4: =F4+H4 -> 10535.54 | J4: =O$1&TEXT(A4,"000") -> 530420240040849246003 | K4: 24442000000246741626 | L4: 2024-06-11 | M4: 91440101094203844N | N4: =IF(A4=1,_xlfn.CONCAT(O3,"001"),IF(A4=2,_xlfn.CONCAT(O3,"002"),IF(A4=11,_xlfn.CONCAT(O3,"011"),"")))
A5: 4 | B5: 传送带 | C5: 千克 | D5: 81 | E5: 85.239 | F5: =E5*D5 -> 6904.359 | G5: 0.03 | H5: =F5*G5 -> 207.13077 | I5: =F5+H5 -> 7111.4898 | J5: =O$1&TEXT(A5,"000") -> 530420240040849246004 | K5: 24442000000246744723 | L5: 2024-06-11 | M5: 91440101094203844N | N5: =IF(A5=1,_xlfn.CONCAT(O4,"001"),IF(A5=2,_xlfn.CONCAT(O4,"002"),IF(A5=11,_xlfn.CONCAT(O4,"011"),"")))
A6: 5 | B6: 传送带 | C6: 千克 | D6: 969 | E6: 85.239 | F6: =E6*D6 -> 82596.591 | G6: 0.03 | H6: =F6*G6 -> 2477.8977 | I6: =F6+H6 -> 85074.489 | J6: =O$1&TEXT(A6,"000") -> 530420240040849246005 | K6: 24442000000246748840 | L6: 2024-06-11 | M6: 91440101094203844N | N6: =IF(A6=1,_xlfn.CONCAT(O5,"001"),IF(A6=2,_xlfn.CONCAT(O5,"002"),IF(A6=11,_xlfn.CONCAT(O5,"011"),"")))
A7: 6 | B7: 钢化玻璃 | C7: 千克 | D7: 142 | E7: 37.742 | F7: =E7*D7 -> 5359.364 | G7: 0.03 | H7: =F7*G7 -> 160.78092 | I7: =F7+H7 -> 5520.1449 | J7: =O$1&TEXT(A7,"000") -> 530420240040849246006 | K7: 24442000000246782528 | L7: 2024-06-11 | M7: 91440101094203844N
A8: 7 | B8: 钢化玻璃 | C8: 千克 | D8: 647 | E8: 37.742 | F8: =E8*D8 -> 24419.074 | G8: 0.03 | H8: =F8*G8 -> 732.57222 | I8: =F8+H8 -> 25151.646 | J8: =O$1&TEXT(A8,"000") -> 530420240040849246007 | K8: 24442000000246800796 | L8: 2024-06-11 | M8: 91440101094203844N
A9: 8 | B9: 钢化玻璃 | C9: 千克 | D9: 75 | E9: 37.742 | F9: =E9*D9 -> 2830.65 | G9: 0.03 | H9: =F9*G9 -> 84.9195 | I9: =F9+H9 -> 2915.5695 | J9: =O$1&TEXT(A9,"000") -> 530420240040849246008 | K9: 24442000000246805415 | L9: 2024-06-11 | M9: 91440101094203844N
A10: 9 | B10: 钢化玻璃 | C10: 千克 | D10: 433 | E10: 37.742 | F10: =E10*D10 -> 16342.286 | G10: 0.03 | H10: =F10*G10 -> 490.26858 | I10: =F10+H10 -> 16832.555 | J10: =O$1&TEXT(A10,"000") -> 530420240040849246009 | K10: 24442000000246892317 | L10: 2024-06-11 | M10: 91440101094203844N
A11: 10 | B11: 支撑柱 | C11: 千克 | D11: 88 | E11: 102.912 | F11: =E11*D11 -> 9056.256 | G11: 0.03 | H11: =F11*G11 -> 271.68768 | I11: =ROUNDUP(F11+H11,0) -> 9328 | J11: =O$1&TEXT(A11,"000") -> 530420240040849246010 | K11: 24442000000246817461 | L11: 2024-06-11 | M11: 91440101094203844N
A12: 小计： | F12: =SUM(F2:F11) -> 212716.42 | G12: 0.03 | H12: =F12*G12 -> 6381.4924 | I12: =F12+H12 -> 219097.91
A13: 11 | B13: 电磁炉 | C13: 个 | D13: 40 | E13: 146.0177 | F13: =E13*D13 -> 5840.708 | G13: 0.13 | H13: =F13*G13 -> 759.29204 | I13: =F13+H13 -> 6600 | J13: =O$1&TEXT(A13,"000") -> 530420240040849246011 | K13: 24442000000240646590 | L13: 2024-06-06 | M13: 91440606673146805K
A14: 12 | B14: 电磁炉 | C14: 个 | D14: 40 | E14: 146.0177 | F14: =E14*D14 -> 5840.708 | G14: 0.13 | H14: =F14*G14 -> 759.29204 | I14: =F14+H14 -> 6600 | J14: =O$1&TEXT(A14,"000") -> 530420240040849246012 | K14: 24442000000240655051 | L14: 2024-06-06 | M14: 91440606673146805K
A15: 13 | B15: 电磁炉 | C15: 个 | D15: 20 | E15: 146.0177 | F15: =E15*D15 -> 2920.354 | G15: 0.13 | H15: =F15*G15 -> 379.64602 | I15: =F15+H15 -> 3300 | J15: =O$1&TEXT(A15,"000") -> 530420240040849246013 | K15: 24442000000240663498 | L15: 2024-06-06 | M15: 91440606673146805K
A16: 14 | B16: 电烤炉 | C16: 个 | D16: 50 | E16: 885.84071 | F16: =E16*D16 -> 44292.035 | G16: 0.13 | H16: =F16*G16 -> 5757.9646 | I16: =F16+H16 -> 50050 | J16: =O$1&TEXT(A16,"000") -> 530420240040849246014 | K16: 24442000000240670535 | L16: 2024-06-06 | M16: 91440606673146805K
A17: 15 | B17: 烤盘 | C17: 个 | D17: 70 | E17: 68.141593 | F17: =E17*D17 -> 4769.9115 | G17: 0.13 | H17: =F17*G17 -> 620.0885 | I17: =F17+H17 -> 5390 | J17: =O$1&TEXT(A17,"000") -> 530420240040849246015 | K17: 24442000000240680254 | L17: 2024-06-06 | M17: 91440606673146805K
A18: 16 | B18: 接油盘 | C18: 个 | D18: 20 | E18: 116.81416 | F18: =E18*D18 -> 2336.2832 | G18: 0.13 | H18: =F18*G18 -> 303.71681 | I18: =F18+H18 -> 2640 | J18: =O$1&TEXT(A18,"000") -> 530420240040849246016 | K18: 24442000000240686615 | L18: 2024-06-06 | M18: 91440606673146805K
A19: 17 | B19: 不锈钢圈 | C19: 个 | D19: 100 | E19: =16.5/(1+G19) -> 14.60177 | F19: =E19*D19 -> 1460.177 | G19: 0.13 | H19: =F19*G19 -> 189.82301 | I19: =F19+H19 -> 1650 | J19: =O$1&TEXT(A19,"000") -> 530420240040849246017 | K19: 24442000000240691472 | L19: 2024-06-06 | M19: 91440606673146805K
A20: 小计： | F20: =SUM(F13:F19) -> 67460.177 | G20: 0.13 | H20: =F20*G20 -> 8769.823 | I20: =F20+H20 -> 76230
A21: 18 | B21: 非金属矿物制品*瓷砖 | C21: 平方米 | D21: 234.24 | E21: 70.349 | F21: =E21*D21 -> 16478.55 | G21: 0.13 | H21: =F21*G21 -> 2142.2115 | I21: =F21+H21 -> 18620.761 | J21: =O$1&TEXT(A21,"000") -> 530420240040849246018 | K21: 24442000000253224954 | L21: 2024-06-14 | M21: 91440604081080339C
A22: 19 | B22: 非金属矿物制品*瓷砖 | C22: 平方米 | D22: 2.88 | E22: 76.48 | F22: =E22*D22 -> 220.2624 | G22: 0.13 | H22: =F22*G22 -> 28.634112 | I22: =F22+H22 -> 248.89651 | J22: =O$1&TEXT(A22,"000") -> 530420240040849246019 | K22: 24442000000253231056 | L22: 2024-06-14 | M22: 91440604081080339C
A23: 小计： | F23: =SUM(F21:F22) -> 16698.812 | G23: 0.13 | H23: =F23*G23 -> 2170.8456 | I23: =F23+H23 -> 18869.658
A24: 总计： | F24: =F12+F23+F20 -> 296875.4 | G24: 0.13 | H24: =H12+H20+H23 -> 17322.161 | I24: =F24+H24 -> 314197.57
I27: =I24-308606.77 -> 5590.7952
